kedro_sagemaker/__init__.py
kedro_sagemaker/cli.py
kedro_sagemaker/cli_functions.py
kedro_sagemaker/client.py
kedro_sagemaker/config.py
kedro_sagemaker/constants.py
kedro_sagemaker/datasets.py
kedro_sagemaker/decorators.py
kedro_sagemaker/docker.py
kedro_sagemaker/generator.py
kedro_sagemaker/runner.py
kedro_sagemaker/utils.py
kedro_sagemaker-0.4.0.dist-info/LICENSE
kedro_sagemaker-0.4.0.dist-info/METADATA
kedro_sagemaker-0.4.0.dist-info/WHEEL
kedro_sagemaker-0.4.0.dist-info/entry_points.txt
kedro_sagemaker-0.4.0.dist-info/RECORD
