Metadata-Version: 2.3
Name: kedro-sagemaker
Version: 0.4.0
Summary: Kedro plugin with AWS SageMaker Pipelines support
License: Apache-2.0
Keywords: kedro,sagemaker,aws,mlops
Author: Marcin Zabłocki
Author-email: marcin.zablocki@getindata.com
Maintainer: GetInData MLOPS
Maintainer-email: mlops@getindata.com
Requires-Python: >=3.9,<4.0
Classifier: Development Status :: 4 - Beta
Classifier: License :: OSI Approved :: Apache Software License
Classifier: Programming Language :: Python :: 3
Classifier: Programming Language :: Python :: 3.9
Classifier: Programming Language :: Python :: 3.10
Classifier: Programming Language :: Python :: 3.11
Classifier: Programming Language :: Python :: 3.12
Classifier: Programming Language :: Python :: 3.13
Requires-Dist: backoff (>=2.2.1)
Requires-Dist: cloudpickle (>=2.2.0)
Requires-Dist: kedro (>=0.19.0)
Requires-Dist: pydantic (>=1.10.2)
Requires-Dist: s3fs (>=2022.11.0)
Requires-Dist: sagemaker (>=2.148.0)
Requires-Dist: tarsafe (>=0.0.4)
Requires-Dist: zstandard (>=0.19.0)
Project-URL: Documentation, https://kedro-sagemaker.readthedocs.io/
Project-URL: Homepage, https://github.com/getindata/kedro-sagemaker
Project-URL: Repository, https://github.com/getindata/kedro-sagemaker
